hydroq_api/__init__.py
hydroq_api-0.1.1.dist-info/LICENSE
hydroq_api-0.1.1.dist-info/METADATA
hydroq_api-0.1.1.dist-info/WHEEL
hydroq_api-0.1.1.dist-info/top_level.txt
hydroq_api-0.1.1.dist-info/RECORD
