Metadata-Version: 2.2
Name: hydroq-api
Version: 0.1.1
Summary: Get your Hydro Quebec electiricty data
Author: Lyubomir Georgiev
License: Apache-2.0
Project-URL: Homepage, https://github.com/lvg77/hydroq-api
Project-URL: Changelog, https://github.com/lvg77/hydroq-api/releases
Project-URL: Issues, https://github.com/lvg77/hydroq-api/issues
Project-URL: CI, https://github.com/lvg77/hydroq-api/actions
Classifier: License :: OSI Approved :: Apache Software License
Requires-Python: >=3.8
License-File: LICENSE
Requires-Dist: pkce>=1.0.3
Requires-Dist: requests>=2.32.3
Provides-Extra: test
Requires-Dist: pytest; extra == "test"
Requires-Dist: requests-mock; extra == "test"
